{
  "structured": [
    {
      "bbox": [
        73,
        9,
        497,
        371
      ],
      "label": "bar",
      "score": 0.9959324681241085
    },
    {
      "bbox": [
        67,
        2,
        508,
        12
      ],
      "label": "axis",
      "score": 0.7
    },
    {
      "bbox": [
        66,
        372,
        510,
        12
      ],
      "label": "axis",
      "score": 0.7
    },
    {
      "bbox": [
        66,
        4,
        510,
        12
      ],
      "label": "axis",
      "score": 0.7
    },
    {
      "bbox": [
        67,
        374,
        508,
        12
      ],
      "label": "axis",
      "score": 0.7
    },
    {
      "bbox": [
        562,
        5,
        12,
        378
      ],
      "label": "axis",
      "score": 0.7
    },
    {
      "bbox": [
        564,
        3,
        12,
        382
      ],
      "label": "axis",
      "score": 0.7
    },
    {
      "bbox": [
        68,
        5,
        12,
        378
      ],
      "label": "axis",
      "score": 0.7
    },
    {
      "bbox": [
        66,
        3,
        12,
        382
      ],
      "label": "axis",
      "score": 0.7
    },
    {
      "bbox": [
        119,
        18,
        354,
        12
      ],
      "label": "line",
      "score": 0.9
    },
    {
      "bbox": [
        91,
        136,
        446,
        187
      ],
      "label": "line",
      "score": 0.9
    },
    {
      "bbox": [
        88,
        123,
        363,
        154
      ],
      "label": "line",
      "score": 0.9
    },
    {
      "bbox": [
        153,
        133,
        376,
        174
      ],
      "label": "line",
      "score": 0.9
    },
    {
      "bbox": [
        148,
        136,
        363,
        207
      ],
      "label": "line",
      "score": 0.9
    },
    {
      "bbox": [
        91,
        124,
        347,
        121
      ],
      "label": "line",
      "score": 0.9
    }
  ],
  "unstructured": [
    {
      "bbox": [
        94,
        25,
        413,
        178
      ],
      "label": "segment",
      "score": 0.8
    }
  ],
  "merged": [
    {
      "bbox": [
        73,
        9,
        497,
        371
      ],
      "label": "bar",
      "score": 0.9959324681241085
    },
    {
      "bbox": [
        66,
        372,
        510,
        12
      ],
      "label": "axis",
      "score": 0.7
    },
    {
      "bbox": [
        67,
        374,
        508,
        12
      ],
      "label": "axis",
      "score": 0.7
    },
    {
      "bbox": [
        562,
        5,
        12,
        378
      ],
      "label": "axis",
      "score": 0.7
    },
    {
      "bbox": [
        564,
        3,
        12,
        382
      ],
      "label": "axis",
      "score": 0.7
    },
    {
      "bbox": [
        68,
        5,
        12,
        378
      ],
      "label": "axis",
      "score": 0.7
    },
    {
      "bbox": [
        66,
        3,
        12,
        382
      ],
      "label": "axis",
      "score": 0.7
    },
    {
      "bbox": [
        119,
        18,
        354,
        12
      ],
      "label": "line",
      "score": 0.9
    },
    {
      "bbox": [
        94,
        25,
        413,
        178
      ],
      "label": "segment",
      "score": 0.8
    },
    {
      "bbox": [
        91,
        133,
        446,
        210
      ],
      "label": "line+line+line",
      "score": 0.9
    },
    {
      "bbox": [
        88,
        123,
        363,
        154
      ],
      "label": "line+line",
      "score": 0.9
    },
    {
      "bbox": [
        66,
        2,
        510,
        14
      ],
      "label": "axis+axis",
      "score": 0.7
    }
  ]
}